[
  {
    "id": 1,
    "question": "ما الفرق الأساسي بين النون الساكنة والتنوين؟",
    "options": [
      "النون أصلية والتنوين زائد",
      "النون لا تُنطق",
      "التنوين يكون في الأفعال",
      "لا يوجد فرق"
    ],
    "correctAnswer": 0,
    "explanation": "النون الساكنة حرف أصلي، أما التنوين فهو زائد"
  },
  {
    "id": 2,
    "question": "كم عدد أحرف الإدغام؟",
    "options": ["4", "5", "6", "7"],
    "correctAnswer": 2,
    "explanation": "أحرف الإدغام ستة مجموعة في كلمة (يرملون)"
  },
  {
    "id": 3,
    "question": "ما حروف الإدغام بغنة؟",
    "options": [
      "ل، ر",
      "ي، ن، م، و",
      "ء، ه، ع",
      "ص، ذ، ث"
    ],
    "correctAnswer": 1,
    "explanation": "الإدغام بغنة يكون في حروف (ينمو)"
  },
  {
    "id": 4,
    "question": "أي الحروف التالية إدغام بدون غنة؟",
    "options": ["ي", "م", "ل", "و"],
    "correctAnswer": 2,
    "explanation": "الإدغام بدون غنة يكون مع اللام والراء"
  },
  {
    "id": 5,
    "question": "ما علامة إدغام التنوين؟",
    "options": [
      "تراكب الحركتين",
      "عدم تراكب الحركتين",
      "وضع ميم صغيرة",
      "تشديد الحرف"
    ],
    "correctAnswer": 1,
    "explanation": "علامة الإدغام عدم تراكب الحركتين"
  },
  {
    "id": 6,
    "question": "ما المقصود بالإظهار الحلقي؟",
    "options": [
      "إدغام النون",
      "إخفاء النون",
      "إخراج الحرف من مخرجه دون غنة",
      "قلب النون ميماً"
    ],
    "correctAnswer": 2,
    "explanation": "الإظهار هو إخراج الحرف من مخرجه من غير غنة"
  },
  {
    "id": 7,
    "question": "كم عدد حروف الإظهار الحلقي؟",
    "options": ["4", "5", "6", "7"],
    "correctAnswer": 2,
    "explanation": "حروف الإظهار ستة"
  },
  {
    "id": 8,
    "question": "أي من الآتي حرف من حروف الإظهار؟",
    "options": ["ب", "م", "غ", "ل"],
    "correctAnswer": 2,
    "explanation": "الغين من حروف الإظهار الحلقي"
  },
  {
    "id": 9,
    "question": "ما حكم النون الساكنة قبل حرف الباء؟",
    "options": [
      "إظهار",
      "إدغام",
      "إقلاب",
      "إخفاء"
    ],
    "correctAnswer": 2,
    "explanation": "النون الساكنة قبل الباء حكمها الإقلاب"
  },
  {
    "id": 10,
    "question": "كيف تُنطق النون في الإقلاب؟",
    "options": [
      "نون مشددة",
      "تحذف تماماً",
      "تُقلب ميماً مع غنة",
      "تُظهر بدون غنة"
    ],
    "correctAnswer": 2,
    "explanation": "تُقلب النون ميماً مع بقاء الغنة"
  },
  {
    "id": 11,
    "question": "ما علامة الإقلاب في المصحف؟",
    "options": [
      "تشديد الحرف",
      "ميم صغيرة فوق النون",
      "تراكب الحركات",
      "سكون فقط"
    ],
    "correctAnswer": 1,
    "explanation": "توضع ميم صغيرة فوق النون الساكنة"
  },
  {
    "id": 12,
    "question": "ما المقصود بالإخفاء الحقيقي؟",
    "options": [
      "إظهار كامل",
      "إدغام كامل",
      "نطق بين الإظهار والإدغام مع غنة",
      "حذف النون"
    ],
    "correctAnswer": 2,
    "explanation": "الإخفاء حالة متوسطة مع بقاء الغنة"
  },
  {
    "id": 13,
    "question": "كم عدد حروف الإخفاء الحقيقي؟",
    "options": ["10", "12", "14", "15"],
    "correctAnswer": 3,
    "explanation": "حروف الإخفاء خمسة عشر حرفاً"
  },
  {
    "id": 14,
    "question": "أي من الآتي مثال على الإخفاء؟",
    "options": [
      "من ربهم",
      "من بعد",
      "من صلصال",
      "من هاد"
    ],
    "correctAnswer": 2,
    "explanation": "الصاد من حروف الإخفاء"
  },
  {
    "id": 15,
    "question": "ما علامة إخفاء التنوين؟",
    "options": [
      "تراكب الحركتين",
      "عدم تراكب الحركتين",
      "ميم صغيرة",
      "تشديد"
    ],
    "correctAnswer": 1,
    "explanation": "علامته عدم تراكب الحركتين"
  }
]
